[{"id":0,"href":"/schudlich/stoutheartpress/docs/about/","title":"About","section":"Docs","content":"# About Stout Heart Press# Tanner Schudlich (he/they) is a social worker, archivist, printmaker, and book binder based in Ypsilanti, MI. Tanner’s work engages with questions about how we navigate grief, memory, hope, and despair in our lives and communities. Tanner uses his own Vandercook 099 cylinder proofing press in addition to community accessible Vandercook No. 3 and No. 1 presses at the University of Michigan Book Arts Studio. When not teaching or working in the U-M Book Arts Studio, he runs Stout Heart Press, a small private press, out of his apartment where he lives with his partner and two cats.\n"},{"id":1,"href":"/schudlich/stoutheartpress/docs/portfolio/","title":"Portfolio","section":"Docs","content":"# Portfolio# Interested in purchasing a print? Visit Stout Heart Press on Etsy# Stout Heart Press Shop Signs of the Times Series# Save Each Other.# Letterpress, Rubber-based ink on paper\nThis print is a part of the Signs of the Times series, which is inspired by the simple boldness of protest signs bearing messages for any historical moment. Wood type for this print was sourced from the University of Michigan Book Arts Studio collection.\nClematis# Multiblock Linocut, Oil-based ink on paper\nInspired by the clematis growing along the side of my grandmother\u0026rsquo;s house. She enjoyed viewing them from the couch in her den. I began carving these blocks on what would have been her 86th birthday.\n"}]